p_terraformer/__init__.py
p_terraformer/cli.py
p_terraformer/cmd/__init__.py
p_terraformer/cmd/args.py
p_terraformer/cmd/aws_generator.py
p_terraformer/cmd/datadog_generator.py
p_terraformer/cmd/p_terraformer_config_generator.py
p_terraformer/cmd/terraform_generator.py
p_terraformer/config/__init__.py
p_terraformer/config/cli_conf.py
p_terraformer/utils/__init__.py
p_terraformer/utils/helpers.py
p_terraformer-0.2.dist-info/LICENSE
p_terraformer-0.2.dist-info/METADATA
p_terraformer-0.2.dist-info/WHEEL
p_terraformer-0.2.dist-info/entry_points.txt
p_terraformer-0.2.dist-info/top_level.txt
p_terraformer-0.2.dist-info/RECORD
